picopayments_hub/__init__.py
picopayments_hub/api.py
picopayments_hub/cli.py
picopayments_hub/cron.py
picopayments_hub/db.py
picopayments_hub/err.py
picopayments_hub/etc.py
picopayments_hub/lib.py
picopayments_hub/sql.py
picopayments_hub/srv.py
picopayments_hub/terms.json
picopayments_hub/verify.py
picopayments_hub/version.py
picopayments_hub/bin/picopayments-hub
picopayments_hub/sql/add_commit_active.sql
picopayments_hub/sql/add_commit_requested.sql
picopayments_hub/sql/add_commit_revoked.sql
picopayments_hub/sql/add_hub_connection.sql
picopayments_hub/sql/add_payment.sql
picopayments_hub/sql/add_revoke_secret.sql
picopayments_hub/sql/add_secret.sql
picopayments_hub/sql/c2h_channel.sql
picopayments_hub/sql/commits_active.sql
picopayments_hub/sql/commits_requested.sql
picopayments_hub/sql/commits_revoked.sql
picopayments_hub/sql/complete_connection.sql
picopayments_hub/sql/get_next_revoke_secret_hash.sql
picopayments_hub/sql/get_secret.sql
picopayments_hub/sql/h2c_channel.sql
picopayments_hub/sql/hub_connection.sql
picopayments_hub/sql/hub_connections_all.sql
picopayments_hub/sql/hub_connections_closed.sql
picopayments_hub/sql/hub_connections_complete.sql
picopayments_hub/sql/hub_connections_open.sql
picopayments_hub/sql/hub_connections_recoverable.sql
picopayments_hub/sql/micropayment_channel.sql
picopayments_hub/sql/migration_0.sql
picopayments_hub/sql/migration_1.sql
picopayments_hub/sql/migration_2.sql
picopayments_hub/sql/migration_3.sql
picopayments_hub/sql/migration_4.sql
picopayments_hub/sql/recv_payments_sum.sql
picopayments_hub/sql/rm_commits.sql
picopayments_hub/sql/send_payments_sum.sql
picopayments_hub/sql/set_commit_notified.sql
picopayments_hub/sql/set_connection_closed.sql
picopayments_hub/sql/set_next_revoke_secret_hash.sql
picopayments_hub/sql/set_payment_notified.sql
picopayments_hub/sql/set_revoke_notified.sql
picopayments_hub/sql/terms.sql
picopayments_hub/sql/unnotified_commit.sql
picopayments_hub-1.0.5.dist-info/DESCRIPTION.rst
picopayments_hub-1.0.5.dist-info/METADATA
picopayments_hub-1.0.5.dist-info/RECORD
picopayments_hub-1.0.5.dist-info/WHEEL
picopayments_hub-1.0.5.dist-info/metadata.json
picopayments_hub-1.0.5.dist-info/top_level.txt
