Metadata-Version: 2.0
Name: picopayments-hub
Version: 1.0.5
Summary: Micropayment hub for counterparty assets.
Home-page: http://storj.io
Author: Fabian Barkhau
Author-email: f483@storj.io
License: MIT
Keywords: storj,counterparty,micropayment,hub
Platform: UNKNOWN
Classifier: Development Status :: 2 - Pre-Alpha
Classifier: Intended Audience :: Developers
Classifier: License :: OSI Approved :: MIT License
Classifier: Operating System :: OS Independent
Classifier: Programming Language :: Python
Classifier: Programming Language :: Python :: 2
Classifier: Programming Language :: Python :: 2.7
Classifier: Programming Language :: Python :: 3
Classifier: Programming Language :: Python :: 3.3
Classifier: Programming Language :: Python :: 3.4
Classifier: Topic :: Software Development :: Libraries :: Python Modules
Requires-Dist: Flask (==0.11)
Requires-Dist: appdirs (==1.4.0)
Requires-Dist: apsw (==3.9.2-r1)
Requires-Dist: btctxstore (==4.8.0)
Requires-Dist: cachetools (==1.1.6)
Requires-Dist: counterparty-lib (==9.55.1)
Requires-Dist: jsonschema (==2.5.1)
Requires-Dist: picopayments-cli (==1.0.4)
Requires-Dist: pyOpenSSL (==16.2.0)
Requires-Dist: pycrypto (==2.6.1)
Requires-Dist: pytest (==2.9.2)
Requires-Dist: pytest-cov (==2.2.1)
Requires-Dist: python-dateutil (==2.5.3)
Requires-Dist: six (==1.10.0)
